{
  "indexes": [
    {
      "collectionGroup": "reviews",
      "queryScope": "COLLECTION",
      "fields": [
        {"fieldPath": "type", "order": "ASCENDING"},
        {"fieldPath": "createdAt", "order": "DESCENDING"}
      ]
    },
    {
      "collectionGroup": "reviews",
      "queryScope": "COLLECTION",
      "fields": [
        {"fieldPath": "status", "order": "ASCENDING"},
        {"fieldPath": "createdAt", "order": "DESCENDING"}
      ]
    },
    {
      "collectionGroup": "containers",
      "queryScope": "COLLECTION",
      "fields": [
        {"fieldPath": "machineId", "order": "ASCENDING"},
        {"fieldPath": "createdAt", "order": "DESCENDING"}
      ]
    },
    {
      "collectionGroup": "containers",
      "queryScope": "COLLECTION",
      "fields": [
        {"fieldPath": "machine.Type", "order": "ASCENDING"},
        {"fieldPath": "createdAt", "order": "DESCENDING"}
      ]
    },
    {
      "collectionGroup": "containers",
      "queryScope": "COLLECTION",
      "fields": [
        {"fieldPath": "uid", "order": "ASCENDING"},
        {"fieldPath": "createdAt", "order": "DESCENDING"}
      ]
    },
    {
      "collectionGroup": "containers",
      "queryScope": "COLLECTION",
      "fields": [
        {"fieldPath": "status", "order": "ASCENDING"},
        {"fieldPath": "createdAt", "order": "DESCENDING"}
      ]
    },
    {
      "collectionGroup": "containers",
      "queryScope": "COLLECTION",
      "fields": [
        {"fieldPath": "containerId", "order": "ASCENDING"},
        {"fieldPath": "createdAt", "order": "DESCENDING"}
      ]
    },
    {
      "collectionGroup": "containers",
      "queryScope": "COLLECTION",
      "fields": [
        {"fieldPath": "type", "order": "ASCENDING"},
        {"fieldPath": "createdAt", "order": "DESCENDING"}
      ]
    },
    {
      "collectionGroup": "payments",
      "queryScope": "COLLECTION",
      "fields": [
        {"fieldPath": "type", "order": "ASCENDING"},
        {"fieldPath": "createdAt", "order": "DESCENDING"}
      ]
    },
    {
      "collectionGroup": "payments",
      "queryScope": "COLLECTION",
      "fields": [
        {"fieldPath": "key", "arrayConfig": "CONTAINS"},
        {"fieldPath": "createdAt", "order": "DESCENDING"}
      ]
    },
    {
      "collectionGroup": "settings",
      "queryScope": "COLLECTION",
      "fields": [
        {"fieldPath": "type", "order": "ASCENDING"},
        {"fieldPath": "tag", "order": "ASCENDING"}
      ]
    }
  ],
  "fieldOverrides": []
}
